README.md
setup.py
ediri_akp/__init__.py
ediri_akp/_inputs.py
ediri_akp/_utilities.py
ediri_akp/cluster.py
ediri_akp/get_cluster.py
ediri_akp/get_clusters.py
ediri_akp/get_instance.py
ediri_akp/instance.py
ediri_akp/outputs.py
ediri_akp/provider.py
ediri_akp/pulumi-plugin.json
ediri_akp/py.typed
ediri_akp.egg-info/PKG-INFO
ediri_akp.egg-info/SOURCES.txt
ediri_akp.egg-info/dependency_links.txt
ediri_akp.egg-info/not-zip-safe
ediri_akp.egg-info/requires.txt
ediri_akp.egg-info/top_level.txt
ediri_akp/config/__init__.py
ediri_akp/config/vars.py